dashboard/__init__.py
dashboard/auth.py
dashboard/main.py
dashboard/plots.py
dashboard/utils.py
dashboard/weather.py
dashboard/weather_plots.py
dashboard/weather_utils.py
dashboard/media/2fts-logo.png
dashboard/media/__init__.py
log_keeper/__init__.py
log_keeper/get_config.py
log_keeper/ingest.py
log_keeper/main.py
log_keeper/output.py
log_keeper/utils.py
log_keeper/weather.py
log_keeper/scripts/__init__.py
log_keeper/scripts/run_log_keeper.bat
viking_log_keeper-2.7.0.data/data/requirements.txt
viking_log_keeper-2.7.0.dist-info/licenses/LICENSE
viking_log_keeper-2.7.0.dist-info/METADATA
viking_log_keeper-2.7.0.dist-info/WHEEL
viking_log_keeper-2.7.0.dist-info/entry_points.txt
viking_log_keeper-2.7.0.dist-info/top_level.txt
viking_log_keeper-2.7.0.dist-info/RECORD
