Metadata-Version: 2.4
Name: viking-log-keeper
Version: 2.7.0
Summary: 661 VGS - Package to collate 2965D log sheets into a master log, database, and dashboard.
Home-page: https://github.com/mjennings061/viking-log-keeper
Author: Michael Jennings
Author-email: mjennings061@gmail.com
License: MIT
Classifier: Programming Language :: Python :: 3
Classifier: License :: OSI Approved :: MIT License
Classifier: Operating System :: OS Independent
License-File: LICENSE
Requires-Dist: extra-streamlit-components~=0.1.81
Requires-Dist: inquirer~=3.4.1
Requires-Dist: keyring~=25.7.0
Requires-Dist: matplotlib~=3.10.8
Requires-Dist: openmeteo-requests~=1.7.5
Requires-Dist: openpyxl~=3.1.0
Requires-Dist: pandas~=2.2.0
Requires-Dist: protobuf~=6.33.4
Requires-Dist: pymongo[srv]~=4.16.0
Requires-Dist: requests-cache~=1.2.1
Requires-Dist: retry-requests~=2.0.0
Requires-Dist: streamlit~=1.53.1
Requires-Dist: tqdm~=4.67.1
Requires-Dist: xlsxwriter~=3.2.9
Requires-Dist: keyrings.alt~=5.0.2
Requires-Dist: secretstorage~=3.5.0
Requires-Dist: setuptools~=80.9.0
Requires-Dist: python-dotenv~=1.0.0
Requires-Dist: pytest~=9.0.2
Requires-Dist: pytest-playwright~=0.7.2
Requires-Dist: pytest-mock~=3.15.1
Requires-Dist: pytest-cov~=7.0.0
Requires-Dist: ruff~=0.14.14
Dynamic: author
Dynamic: author-email
Dynamic: classifier
Dynamic: description
Dynamic: description-content-type
Dynamic: home-page
Dynamic: license
Dynamic: license-file
Dynamic: requires-dist
Dynamic: summary
